aliyunsdksmc/__init__.py
aliyunsdksmc/endpoint.py
aliyunsdksmc/request/__init__.py
aliyunsdksmc/request/v20190601/AssociateSourceServersRequest.py
aliyunsdksmc/request/v20190601/CreateAccessTokenRequest.py
aliyunsdksmc/request/v20190601/CreateCrossZoneMigrationJobRequest.py
aliyunsdksmc/request/v20190601/CreateReplicationJobRequest.py
aliyunsdksmc/request/v20190601/CreateWorkgroupRequest.py
aliyunsdksmc/request/v20190601/CutOverReplicationJobRequest.py
aliyunsdksmc/request/v20190601/DeleteAccessTokenRequest.py
aliyunsdksmc/request/v20190601/DeleteReplicationJobRequest.py
aliyunsdksmc/request/v20190601/DeleteSourceServerRequest.py
aliyunsdksmc/request/v20190601/DeleteWorkgroupRequest.py
aliyunsdksmc/request/v20190601/DescribeReplicationJobsRequest.py
aliyunsdksmc/request/v20190601/DescribeSourceServersRequest.py
aliyunsdksmc/request/v20190601/DescribeWorkgroupsRequest.py
aliyunsdksmc/request/v20190601/DisableAccessTokenRequest.py
aliyunsdksmc/request/v20190601/DisassociateSourceServersRequest.py
aliyunsdksmc/request/v20190601/ListAccessTokensRequest.py
aliyunsdksmc/request/v20190601/ListTagResourcesRequest.py
aliyunsdksmc/request/v20190601/ModifyReplicationJobAttributeRequest.py
aliyunsdksmc/request/v20190601/ModifySourceServerAttributeRequest.py
aliyunsdksmc/request/v20190601/ModifyWorkgroupAttributeRequest.py
aliyunsdksmc/request/v20190601/StartReplicationJobRequest.py
aliyunsdksmc/request/v20190601/StopReplicationJobRequest.py
aliyunsdksmc/request/v20190601/TagResourcesRequest.py
aliyunsdksmc/request/v20190601/UntagResourcesRequest.py
aliyunsdksmc/request/v20190601/__init__.py
aliyun_python_sdk_smc-1.0.4.dist-info/LICENSE
aliyun_python_sdk_smc-1.0.4.dist-info/METADATA
aliyun_python_sdk_smc-1.0.4.dist-info/WHEEL
aliyun_python_sdk_smc-1.0.4.dist-info/top_level.txt
aliyun_python_sdk_smc-1.0.4.dist-info/RECORD
